.VERSION
AUTHORS.rst
CONTRIBUTING.rst
HISTORY.rst
LICENSE
MANIFEST.in
README.rst
USAGE.rst
requirements.txt
setup.py
docs/Makefile
docs/authors.rst
docs/conf.py
docs/contributing.rst
docs/footylib.rst
docs/history.rst
docs/index.rst
docs/installation.rst
docs/modules.rst
docs/readme.rst
docs/usage.rst
footylib/.VERSION
footylib/__init__.py
footylib/_version.py
footylib/footylib.py
footylib/footylibExceptions.py
footylib.egg-info/PKG-INFO
footylib.egg-info/SOURCES.txt
footylib.egg-info/dependency_links.txt
footylib.egg-info/not-zip-safe
footylib.egg-info/requires.txt
footylib.egg-info/top_level.txt