Metadata-Version: 1.1
Name: footylib
Version: 3.0.2
Summary: Get season matches for Footy.eu
Home-page: https://github.com/wefner/footy
Author: Oriol Fabregas
Author-email: fabregas.oriol@gmail.com
License: Apache-2.0
Keywords: footylib
Platform: UNKNOWN
Classifier: Development Status :: 5 - Production/Stable
Classifier: License :: OSI Approved :: Apache Software License
Classifier: Natural Language :: English
Classifier: Programming Language :: Python :: 2.7
